odoo/addons/agreement_sign_oca/README.rst
odoo/addons/agreement_sign_oca/__init__.py
odoo/addons/agreement_sign_oca/__manifest__.py
odoo/addons/agreement_sign_oca/oca_dependencies.txt
odoo/addons/agreement_sign_oca/data/data.xml
odoo/addons/agreement_sign_oca/demo/sign_oca_template.xml
odoo/addons/agreement_sign_oca/i18n/agreement_sign_oca.pot
odoo/addons/agreement_sign_oca/i18n/es.po
odoo/addons/agreement_sign_oca/i18n/it.po
odoo/addons/agreement_sign_oca/models/__init__.py
odoo/addons/agreement_sign_oca/models/agreement.py
odoo/addons/agreement_sign_oca/models/res_company.py
odoo/addons/agreement_sign_oca/models/res_config_settings.py
odoo/addons/agreement_sign_oca/models/sign_oca_request.py
odoo/addons/agreement_sign_oca/readme/CONFIGURE.md
odoo/addons/agreement_sign_oca/readme/CONTRIBUTORS.md
odoo/addons/agreement_sign_oca/readme/DESCRIPTION.md
odoo/addons/agreement_sign_oca/readme/USAGE.md
odoo/addons/agreement_sign_oca/static/description/icon.png
odoo/addons/agreement_sign_oca/static/description/index.html
odoo/addons/agreement_sign_oca/tests/__init__.py
odoo/addons/agreement_sign_oca/tests/test_agreement_sign_oca.py
odoo/addons/agreement_sign_oca/views/agreement_views.xml
odoo/addons/agreement_sign_oca/views/res_config_settings_view.xml
odoo/addons/agreement_sign_oca/views/sign_oca_request_views.xml
odoo_addon_agreement_sign_oca-17.0.1.1.0.1.dist-info/METADATA
odoo_addon_agreement_sign_oca-17.0.1.1.0.1.dist-info/WHEEL
odoo_addon_agreement_sign_oca-17.0.1.1.0.1.dist-info/top_level.txt
odoo_addon_agreement_sign_oca-17.0.1.1.0.1.dist-info/RECORD
